nbinteract/__init__.py
nbinteract/cli.py
nbinteract/exporters.py
nbinteract/plotting.0.py
nbinteract/plotting.1.py
nbinteract/plotting.py
nbinteract/preprocessors.py
nbinteract/questions.py
nbinteract/util.py
nbinteract/templates/full.tpl
nbinteract/templates/local.tpl
nbinteract/templates/nbinteract_css.tpl
nbinteract/templates/partial.tpl
nbinteract/templates/plain.tpl
j1_nbinteract-1.0.7.dist-info/LICENSE.txt
j1_nbinteract-1.0.7.dist-info/METADATA
j1_nbinteract-1.0.7.dist-info/WHEEL
j1_nbinteract-1.0.7.dist-info/entry_points.txt
j1_nbinteract-1.0.7.dist-info/top_level.txt
j1_nbinteract-1.0.7.dist-info/RECORD
