Metadata-Version: 2.1
Name: j1-nbinteract
Version: 1.0.7
Summary: Export interactive HTML pages from Jupyter Notebooks for J1 Template
Home-page: https://github.com/jekyll-one/j1-nbinteract
Author: Juergen Adams
Author-email: jadams@gmx.de
License: MIT
Keywords: jupyter nbconvert interact
Platform: UNKNOWN
Classifier: Development Status :: 5 - Production/Stable
Classifier: Intended Audience :: Information Technology
Classifier: Topic :: Software Development :: Build Tools
Classifier: License :: OSI Approved :: MIT License
Classifier: Programming Language :: Python :: 3
Classifier: Programming Language :: Python :: 3.7
Classifier: Programming Language :: Python :: 3.8
Classifier: Programming Language :: Python :: 3.9
Classifier: Framework :: Jupyter
Requires-Dist: ipython (<8,>=6)
Requires-Dist: ipywidgets (<8,>=7.5.0)
Requires-Dist: toolz (<1,>=0.8)
Requires-Dist: docopt (<1,>=0.6.2)
Requires-Dist: numpy (<2,>=1)
Requires-Dist: nbformat (>=5.0)
Requires-Dist: traitlets (>=5.0)
Requires-Dist: bqplot (==0.11.9)
Requires-Dist: jinja2 (==3.0)
Requires-Dist: nbconvert (<7,>=5.6)
Requires-Dist: markupsafe (==2.0.1)
Provides-Extra: dev
Requires-Dist: check-manifest ; extra == 'dev'
Provides-Extra: test
Requires-Dist: pytest ; extra == 'test'
Requires-Dist: coverage ; extra == 'test'
Requires-Dist: coveralls ; extra == 'test'
